Metadata-Version: 2.1
Name: dirlister
Version: 1.0.0
Summary: Generates wordlists to use for enumeration and brute-forcing files and directories
Home-page: https://github.com/jimmy-ly00/dirlister
Author: Jimmy Ly
Author-email: jimmy-ly00@proton.me
License: GPL-2.0
Classifier: License :: OSI Approved :: GNU General Public License v2 (GPLv2)
Classifier: Programming Language :: Python
Classifier: Programming Language :: Python :: 2
Classifier: Programming Language :: Python :: 2.7
Classifier: Programming Language :: Python :: 3
Classifier: Programming Language :: Python :: 3.8
Classifier: Programming Language :: Python :: 3.9
Classifier: Programming Language :: Python :: 3.10
Classifier: Programming Language :: Python :: 3.11
Classifier: Programming Language :: Python :: 3.12
Requires-Python: >=2.7
License-File: LICENSE
